{"resourceType":"StructureDefinition","id":"icd-10-gm-mehrfachcodierungs-kennzeichen","url":"http://fhir.de/StructureDefinition/icd-10-gm-mehrfachcodierungs-kennzeichen","version":"1.3.2","name":"ExtensionMehrfachcodierungKennzeichen","title":"Mehrfachkodierungs-Kennzeichen bei  ICD-10-gm","status":"draft","fhirVersion":"4.0.1","kind":"complex-type","abstract":false,"context":[{"type":"element","expression":"Condition.code.coding"}],"type":"Extension","baseDefinition":"http://hl7.org/fhir/StructureDefinition/Extension","derivation":"constraint","differential":{"element":[{"id":"Extension.url","path":"Extension.url","fixedUri":"http://fhir.de/StructureDefinition/icd-10-gm-mehrfachcodierungs-kennzeichen"},{"id":"Extension.value[x]","path":"Extension.value[x]","min":1,"type":[{"code":"Coding"}],"binding":{"strength":"required","valueSet":"http://fhir.de/ValueSet/icd-10-gm-mehrfachcodierungs-kennzeichen"}},{"id":"Extension.value[x].system","path":"Extension.value[x].system","min":1},{"id":"Extension.value[x].code","path":"Extension.value[x].code","min":1}]}}